irs/QM_combiner.py
irs/__init__.py
irs/ir_Structure.py
irs/data/dict_fg_IR_data.json
irs/data/dict_fg_detection.json
irspectrum_sim-0.0.3.dist-info/licenses/LICENSE
irspectrum_sim-0.0.3.dist-info/METADATA
irspectrum_sim-0.0.3.dist-info/WHEEL
irspectrum_sim-0.0.3.dist-info/top_level.txt
irspectrum_sim-0.0.3.dist-info/RECORD
