Metadata-Version: 2.4
Name: irspectrum-sim
Version: 0.0.3
Summary: Infrared Spectrum Simulator using Streamlit, Psi4 and ORCA
Author-email: Hugo Praz <hugo.praz@epfl.ch>, Ryans Chen <ryans.chen@epfl.ch>, Anders Eggen <anders.eggen@epfl.ch>
License: MIT License
Project-URL: source, https://github.com/ryanschen0/IRS
Project-URL: tracker, https://github.com/ryanschen0/IRS/issues
Classifier: Development Status :: 3 - Alpha
Classifier: Intended Audience :: Developers
Classifier: License :: OSI Approved :: MIT License
Classifier: Operating System :: OS Independent
Classifier: Programming Language :: Python
Classifier: Programming Language :: Python :: 3.10
Classifier: Programming Language :: Python :: 3.11
Requires-Python: >=3.10
License-File: LICENSE
Requires-Dist: rdkit
Requires-Dist: streamlit
Requires-Dist: pubchempy
Requires-Dist: numpy
Requires-Dist: matplotlib
Requires-Dist: py3Dmol
Provides-Extra: test
Requires-Dist: hypothesis; extra == "test"
Requires-Dist: pytest; extra == "test"
Requires-Dist: pytest-cov; extra == "test"
Requires-Dist: tox; extra == "test"
Requires-Dist: genbadge[coverage]; extra == "test"
Provides-Extra: doc
Requires-Dist: furo; extra == "doc"
Requires-Dist: myst-parser; extra == "doc"
Requires-Dist: sphinx>=5; extra == "doc"
Requires-Dist: sphinx-copybutton; extra == "doc"
Dynamic: license-file
